odoo8_addon_l10n_id_taxform_period-8.0.1.0.0-py2.7-nspkg.pth
odoo_addons/l10n_id_taxform_period/__openerp__.py
odoo_addons/l10n_id_taxform_period/__init__.py
odoo_addons/l10n_id_taxform_period/README.rst
odoo_addons/l10n_id_taxform_period/security/ir.model.access.csv
odoo_addons/l10n_id_taxform_period/models/tax_period.py
odoo_addons/l10n_id_taxform_period/models/__init__.py
odoo_addons/l10n_id_taxform_period/views/tax_period_views.xml
odoo_addons/l10n_id_taxform_period/tests/__init__.py
odoo_addons/l10n_id_taxform_period/tests/test_tax_period.py
odoo_addons/l10n_id_taxform_period/demo/tax_period_demo.xml
odoo_addons/l10n_id_taxform_period/static/description/icon.png
odoo8_addon_l10n_id_taxform_period-8.0.1.0.0.dist-info/top_level.txt
odoo8_addon_l10n_id_taxform_period-8.0.1.0.0.dist-info/WHEEL
odoo8_addon_l10n_id_taxform_period-8.0.1.0.0.dist-info/RECORD
odoo8_addon_l10n_id_taxform_period-8.0.1.0.0.dist-info/metadata.json
odoo8_addon_l10n_id_taxform_period-8.0.1.0.0.dist-info/DESCRIPTION.rst
odoo8_addon_l10n_id_taxform_period-8.0.1.0.0.dist-info/METADATA
odoo8_addon_l10n_id_taxform_period-8.0.1.0.0.dist-info/namespace_packages.txt
